PremaDjango/__init__.py
PremaDjango/settings.py
PremaDjango/middlewares/__init__.py
PremaDjango/middlewares/redis_cache_disable.py
PremaDjango/models/__init__.py
PremaDjango/models/field_converters.py
PremaDjango/models/field_validators.py
PremaDjango/response_handlers/__init__.py
PremaDjango/response_handlers/custom_response_handlre.py
PremaDjango-1.0.6.dist-info/LICENSE.txt
PremaDjango-1.0.6.dist-info/METADATA
PremaDjango-1.0.6.dist-info/WHEEL
PremaDjango-1.0.6.dist-info/top_level.txt
PremaDjango-1.0.6.dist-info/RECORD
