Metadata-Version: 2.1
Name: PremaDjango
Version: 1.0.6
Summary: configurations and settings.
Home-page: https://github.com/prema1432/premadjango/
Author: Premanath
Author-email: talamarlapremanath143@gmail.com
License: MIT
Classifier: Programming Language :: Python :: 3
Classifier: Framework :: Django
License-File: LICENSE.txt
Requires-Dist: Django
Requires-Dist: setuptools-scm
Requires-Dist: requests
